Kronos_heureka_code/KronosException.py
Kronos_heureka_code/__VergleichsStamm.py
Kronos_heureka_code/__init__.py
Kronos_heureka_code/Notationen/DatumsNotationen.py
Kronos_heureka_code/Notationen/UhrzeitNotationen.py
Kronos_heureka_code/Notationen/__init__.py
Kronos_heureka_code/Zeit/ZeitException.py
Kronos_heureka_code/Zeit/__init__.py
Kronos_heureka_code/Zeit/Datum/Datum.py
Kronos_heureka_code/Zeit/Datum/DatumException.py
Kronos_heureka_code/Zeit/Datum/__init__.py
Kronos_heureka_code/Zeit/Datum/Jahr/Jahr.py
Kronos_heureka_code/Zeit/Datum/Jahr/JahrException.py
Kronos_heureka_code/Zeit/Datum/Jahr/Zeitrechnung.py
Kronos_heureka_code/Zeit/Datum/Jahr/__init__.py
Kronos_heureka_code/Zeit/Datum/Monat/AnzahlTageImMonat.py
Kronos_heureka_code/Zeit/Datum/Monat/Monat.py
Kronos_heureka_code/Zeit/Datum/Monat/MonatsException.py
Kronos_heureka_code/Zeit/Datum/Monat/Monatscode.py
Kronos_heureka_code/Zeit/Datum/Monat/Monatsname.py
Kronos_heureka_code/Zeit/Datum/Monat/Monatsposition.py
Kronos_heureka_code/Zeit/Datum/Monat/__init__.py
Kronos_heureka_code/Zeit/Datum/Tag/Tag.py
Kronos_heureka_code/Zeit/Datum/Tag/TagException.py
Kronos_heureka_code/Zeit/Datum/Tag/__init__.py
Kronos_heureka_code/Zeit/Datum/Wochentag/Wochentag.py
Kronos_heureka_code/Zeit/Datum/Wochentag/WochentagException.py
Kronos_heureka_code/Zeit/Datum/Wochentag/WochentagName.py
Kronos_heureka_code/Zeit/Datum/Wochentag/WochentagPosition.py
Kronos_heureka_code/Zeit/Datum/Wochentag/__init__.py
Kronos_heureka_code/Zeit/Uhrzeit/Uhrzeit.py
Kronos_heureka_code/Zeit/Uhrzeit/UhrzeitException.py
Kronos_heureka_code/Zeit/Uhrzeit/__init__.py
Kronos_heureka_code/Zeit/Uhrzeit/Minute/Minute.py
Kronos_heureka_code/Zeit/Uhrzeit/Minute/MinuteException.py
Kronos_heureka_code/Zeit/Uhrzeit/Minute/__init__.py
Kronos_heureka_code/Zeit/Uhrzeit/Sekunde/Sekunde.py
Kronos_heureka_code/Zeit/Uhrzeit/Sekunde/SekundeException.py
Kronos_heureka_code/Zeit/Uhrzeit/Sekunde/__init__.py
Kronos_heureka_code/Zeit/Uhrzeit/Stunde/Stunde.py
Kronos_heureka_code-1.0.1.1.dist-info/LICENSE.txt
Kronos_heureka_code-1.0.1.1.dist-info/METADATA
Kronos_heureka_code-1.0.1.1.dist-info/WHEEL
Kronos_heureka_code-1.0.1.1.dist-info/top_level.txt
Kronos_heureka_code-1.0.1.1.dist-info/RECORD
