Metadata-Version: 2.1
Name: Kronos-heureka-code
Version: 1.0.1.1
Summary: Bietet die Verwaltung von Daten und Uhrzeiten
Home-page: https://github.com/heureka-code/Kronos-heureka-code
Author: heureka-code
License: MIT
Download-URL: https://github.com/heureka-code/Kronos-heureka-code/archive/refs/tags/1.0.1.1.tar.gz
Platform: UNKNOWN
License-File: LICENSE.txt
